.gitignore
readme.md
setup.py
sneaze.py
resources/__init__.py
resources/logo.png
resources/logo_error.png
resources/logo_fail.png
resources/logo_pass.png
sneazr.egg-info/PKG-INFO
sneazr.egg-info/SOURCES.txt
sneazr.egg-info/dependency_links.txt
sneazr.egg-info/entry_points.txt
sneazr.egg-info/requires.txt
sneazr.egg-info/top_level.txt