Metadata-Version: 1.0
Name: sneazr
Version: 0.1
Summary: Have nosetests notify to growl
Home-page: http://github.com/jessemiller/Sneazr
Author: Jesse Miller
Author-email: millerjesse@gmail.com
License: UNKNOWN
Keywords: nose tests growl
Platform: UNKNOWN
